edfi_lms_harmonizer/__init__.py
edfi_lms_harmonizer/__main__.py
edfi_lms_harmonizer/exceptions_reports.py
edfi_lms_harmonizer/harmonizer.py
edfi_lms_harmonizer/helpers/__init__.py
edfi_lms_harmonizer/helpers/argparser.py
edfi_lms_harmonizer/helpers/constants.py
edfi_lms_harmonizer/migrator.py
edfi_lms_harmonizer/runner.py
edfi_lms_harmonizer/scripts/mssql/0001_initialize_lms_database.sql
edfi_lms_harmonizer/scripts/mssql/0002_harmonize_lmsuser_canvas.sql
edfi_lms_harmonizer/scripts/mssql/0003_harmonize_lmsuser_schoology.sql
edfi_lms_harmonizer/scripts/mssql/0004_harmonize_lmsuser_google-classroom.sql
edfi_lms_harmonizer/scripts/mssql/0005_harmonize_lmssection_canvas.sql
edfi_lms_harmonizer/scripts/mssql/0006_harmonize_lmssection_google_classroom.sql
edfi_lms_harmonizer/scripts/mssql/0007_harmonize_lmssection_schoology.sql
edfi_lms_harmonizer/scripts/mssql/0008_view_exceptions_LMSSection.sql
edfi_lms_harmonizer/scripts/mssql/0009_view_exceptions_LMSUser.sql
edfi_lms_harmonizer/scripts/mssql/0010_harmonize_assignment.sql
edfi_lms_harmonizer/scripts/mssql/0011_harmonize_assignment_submissions.sql
edfi_lms_harmonizer/scripts/mssql/0012_view_missing_assignment_category_descriptors.sql
edfi_lms_harmonizer/scripts/mssql/0013_view_missing_assignmentsubmission_status_descriptors.sql
edfi_lms_harmonizer/scripts/mssql/0014_view_assignment_submissions_exceptions.sql
edfi_lms_harmonizer/scripts/mssql/0015_view_assignments_exceptions.sql
edfi_lms_harmonizer/scripts/postgresql/0001_initialize_lms_database.sql
edfi_lms_harmonizer/scripts/postgresql/0002_harmonize_lmsuser_canvas.sql
edfi_lms_harmonizer/scripts/postgresql/0003_harmonize_lmsuser_schoology.sql
edfi_lms_harmonizer/scripts/postgresql/0004_harmonize_lmsuser_google-classroom.sql
edfi_lms_harmonizer/scripts/postgresql/0005_harmonize_lmssection_canvas.sql
edfi_lms_harmonizer/scripts/postgresql/0006_harmonize_lmssection_google_classroom.sql
edfi_lms_harmonizer/scripts/postgresql/0007_harmonize_lmssection_schoology.sql
edfi_lms_harmonizer-1.2.2.dist-info/METADATA
edfi_lms_harmonizer-1.2.2.dist-info/WHEEL
edfi_lms_harmonizer-1.2.2.dist-info/RECORD
