Metadata-Version: 2.1
Name: edfi-lms-harmonizer
Version: 1.2.2
Summary: Ed-Fi LMS Toolkit Harmonizer
Home-page: https://docs.ed-fi.org/getting-started/edfi-exchange/technology/ed-fi-lms-toolkit
License: Apache-2.0
Author: Ed-Fi Alliance, LLC and contributors
Requires-Python: >3.9.1,<4.0.0
Classifier: License :: OSI Approved :: Apache Software License
Classifier: Programming Language :: Python :: 3
Classifier: Programming Language :: Python :: 3.10
Classifier: Programming Language :: Python :: 3.11
Classifier: Programming Language :: Python :: 3.12
Requires-Dist: ConfigArgParse (>=1.4.1,<2.0.0)
Requires-Dist: SQLAlchemy (==1.3.23)
Requires-Dist: cryptography (>=44.0.1,<45.0.0)
Requires-Dist: edfi-lms-extractor-lib (>=1.1.0,<2.0.0)
Requires-Dist: edfi-sql-adapter (>=1.0.3,<2.0.0)
Requires-Dist: errorhandler (>=2.0.1,<3.0.0)
Requires-Dist: numpy (>=1,<2)
Requires-Dist: pandas (<2.0.0)
Requires-Dist: pyodbc (>=4.0.30,<5.0.0)
Requires-Dist: python-dotenv (>=0.17.1,<0.18.0)
Requires-Dist: sqlparse (>=0.4.1,<0.6.0)
Project-URL: Repository, https://github.com/Ed-Fi-Exchange-OSS/LMS-Toolkit
